[
 {
   "Position": "President",
   "Name": "Alif Arshad Bakshi"
 },
 {
   "Position": "Vice President (Management)",
   "Name": "Md. Tanvir Hossain Saikat"
 },
 {
   "Position": "Vice President (Finance)",
   "Name": "Shahriar Mahmud"
 },
 {
   "Position": "Treasurer",
   "Name": "Naimul Haque"
 },
 {
   "Position": "Moderator (Student Body)",
   "Name": "Farhan Fuad"
 },
 {
   "Position": "Volunteer Coordinator (CSE)",
   "Name": "Faria Ahmed"
 },
 {
   "Position": "Volunteer Coordinator (SWE)",
   "Name": "Arafat Kabir Khan"
 },
 {
   "Position": "Event Management Executive (CTF)",
   "Name": "Sumit Alam Khan"
 },
 {
   "Position": "Event Management Executive (Esports)",
   "Name": "MD. Ahnaf Akib"
 },
 {
   "Position": "Event Management Executive (Esports)",
   "Name": "H.M.Shadid Reza Chowdhury"
 },
 {
   "Position": "Event Management Executive (Hackathon)",
   "Name": "Navid Hasin Alvee"
 },
 {
   "Position": "Event Management Executive (IT Business Case)",
   "Name": "Sajid Ahmed Chowdhury"
 },
 {
   "Position": "Event Management Executive (AI and Machine Learning)",
   "Name": "MD Mohaymen Ul Anam"
 },
 {
   "Position": "Event Management Executive (Olympiad)",
   "Name": "A. K. M. Rakinuzzaman"
 },
 {
   "Position": "Event Management Executive (Programming)",
   "Name": "Moudud Hasan"
 },
 {
   "Position": "Event Management Executive (Seminar And Workshop)",
   "Name": "Tasfia Tasneem Annesha"
 },
 {
   "Position": "Event Management Executive (Seminar And Workshop)",
   "Name": "Zaarin Anjum"
 },
 {
   "Position": "Executive Secretary (Prize Management)",
   "Name": "Syem Aziz"
 },
 {
   "Position": "Executive Secretary (Reception)",
   "Name": "Lamiya Tahsin Orpa"
 },
 {
   "Position": "Executive Secretary (Refreshments)",
   "Name": "Md Hasibul Hasan Rafit"
 },
 {
   "Position": "Executive Secretary (Transport)",
   "Name": "Anik Emtiaz"
 },
 {
   "Position": "Executive Secretary (PR and Marketing)",
   "Name": "Rahanuma Ryaan Ferdous"
 },
 {
   "Position": "Operations Executice (Public Relation)",
   "Name": "Suraiya Hasan"
 },
 {
   "Position": "Operations Executive (Design)",
   "Name": "Reaz Hassan Joarder"
 },
 {
   "Position": "Operations Executive (Design)",
   "Name": "Sherajul Arifin"
 },
 {
   "Position": "Operations Executive (Logistics)",
   "Name": "Rakin Abrar"
 },
 {
   "Position": "Operations Executive (Logistics)",
   "Name": "Nafisa Tabassum Oeshy"
 },
 {
   "Position": "Operations Executive (Photography and Digital Media)",
   "Name": "Anika Tahsin"
 },
 {
   "Position": "Operations Executive (Sponsorship And Liaison)",
   "Name": "Alin Mohammad Sifayet"
 },
 {
   "Position": "Operations Executive (Sponsorship And Liaison)",
   "Name": "Sakibul Islam"
 },
 {
   "Position": "Publications Executive",
   "Name": "Sidratul Tanzila Tasmi"
 },
 {
   "Position": "Web Development Executive",
   "Name": "Sakif Ahbab"
 },
 {
   "Position": "International Student Executive",
   "Name": "Sabry Said Sabry Ragab"
 }
]